README
setup.cfg
setup.py
Restpose.egg-info/PKG-INFO
Restpose.egg-info/SOURCES.txt
Restpose.egg-info/dependency_links.txt
Restpose.egg-info/not-zip-safe
Restpose.egg-info/requires.txt
Restpose.egg-info/top_level.txt
restpose/__init__.py
restpose/client.py
restpose/errors.py
restpose/query.py
restpose/resource.py
restpose/version.py
restpose/unittests/__init__.py
restpose/unittests/category_test.py
restpose/unittests/helpers.py
restpose/unittests/index_test.py
restpose/unittests/query_test.py
restpose/unittests/resource_test.py
restpose/unittests/search_test.py