Metadata-Version: 1.0
Name: Restpose
Version: 0.7.7
Summary: Client for the Restpose Server
Home-page: https://github.com/restpose/restpose-py
Author: Richard Boulton
Author-email: richard@tartarus.org
License: MIT
Platform: any
Classifier: Development Status :: 3 - Alpha
Classifier: Environment :: Console
Classifier: License :: OSI Approved :: MIT License
Classifier: Programming Language :: Python :: 2.7
Classifier: Operating System :: Unix
